Metadata-Version: 1.0
Name: github-collective
Version: 0.4
Summary: Script to manage GitHub organizations in a collective manner
Home-page: https://github.com/collective/github-collective
Author: Rok Garbas
Author-email: rok@garbas.si
License: BSD
Keywords: github git permission collaboration collective organization
Platform: UNKNOWN
Classifier: Development Status :: 5 - Production/Stable
Classifier: Environment :: Console
Classifier: Intended Audience :: System Administrators
Classifier: License :: OSI Approved :: BSD License
Classifier: Operating System :: OS Independent
Classifier: Programming Language :: Python :: 2.6
Classifier: Programming Language :: Python :: 2.7
